dbt/__init__.py
dbt/adapters/__init__.py
dbt/adapters/oracle/__init__.py
dbt/adapters/oracle/connections.py
dbt/adapters/oracle/impl.py
dbt/adapters/oracle/relation.py
dbt/include/__init__.py
dbt/include/oracle/__init__.py
dbt/include/oracle/dbt_project.yml
dbt/include/oracle/sample_profiles.yml
dbt/include/oracle/macros/adapters.sql
dbt/include/oracle/macros/catalog.sql
dbt/include/oracle/macros/oracle_utils.sql
dbt/include/oracle/macros/seeds.sql
dbt/include/oracle/macros/snapshots.sql
dbt/include/oracle/macros/strategies.sql
dbt/include/oracle/macros/tests.sql
test/__init__.py
test/integration/__init__.py
test/integration/base.py
test/unit/__init__.py
test/unit/test_oracle.py
test/unit/utils.py
oracle4dbt-0.0.2.dist-info/LICENSE
oracle4dbt-0.0.2.dist-info/METADATA
oracle4dbt-0.0.2.dist-info/WHEEL
oracle4dbt-0.0.2.dist-info/top_level.txt
oracle4dbt-0.0.2.dist-info/RECORD
