Metadata-Version: 2.1
Name: oracle4dbt
Version: 0.0.2
Summary: The oracle adapter plugin for dbt (data build tool)
Home-page: https://github.com/rsella/oracle4dbt
Author: rsella
Author-email: rsella94@gmail.com
License: UNKNOWN
Platform: UNKNOWN
Requires-Python: >=3.5
Requires-Dist: dbt-core (>=0.19.0)
Requires-Dist: cx-Oracle
